[{
  "_id": {
    "$oid": "6055b0bf24516ccec098e6ba"
  },
  "username": "iit2019109",
  "c1_sub1": 15,
  "c1_sub2": 20,
  "c1_sub3": 15,
  "c1_sub4": 15,
  "c1_sub5": 15,
  "c2_sub1": 15,
  "c2_sub2": 20,
  "c2_sub3": 15,
  "c2_sub4": 15,
  "c2_sub5": 15,
  "c3_sub1": 25,
  "c3_sub2": 20,
  "c3_sub3": 25,
  "c3_sub4": 25,
  "c3_sub5": 25,
  "sub1": "Design and Analysis of Algorithms",
  "sub2": "Principles of Programming Language",
  "sub3": "Computer Networks",
  "sub4": "Software Engineering",
  "sub5": "Database Management System",
  "c1_ele1": 0,
  "c1_ele2": 0,
  "c1_ele3": 0,
  "c2_ele1": 0,
  "c2_ele2": 0,
  "c2_ele3": 0,
  "c3_ele1": 0,
  "c3_ele2": 0,
  "c3_ele3": 0,
  "ele1": "-",
  "ele2": "-",
  "ele3": "-",
  "mp1": "-",
  "mp2": "-",
  "c1_mp1": 0,
  "c1_mp2": 0,
  "c2_mp1": 0,
  "c2_mp2": 0,
  "c3_mp1": 0,
  "c3_mp2": 0
},{
  "_id": {
    "$oid": "6062b0117f26a94399cab5da"
  },
  "username": "iit2019111",
  "c1_sub1": 15,
  "c1_sub2": 15,
  "c1_sub3": 15,
  "c1_sub4": 15,
  "c1_sub5": 15,
  "c2_sub1": 15,
  "c2_sub2": 15,
  "c2_sub3": 15,
  "c2_sub4": 15,
  "c2_sub5": 15,
  "c3_sub1": 25,
  "c3_sub2": 25,
  "c3_sub3": 25,
  "c3_sub4": 25,
  "c3_sub5": 25,
  "sub1": "Design and Analysis of Algorithms",
  "sub2": "Principles of Programming Language",
  "sub3": "Computer Networks",
  "sub4": "Software Engineering",
  "sub5": "Database Management System",
  "c1_ele1": 0,
  "c1_ele2": 0,
  "c1_ele3": 0,
  "c2_ele1": 0,
  "c2_ele2": 0,
  "c2_ele3": 0,
  "c3_ele1": 0,
  "c3_ele2": 0,
  "c3_ele3": 0,
  "ele1": "-",
  "ele2": "-",
  "ele3": "-",
  "mp1": "-",
  "mp2": "-",
  "c1_mp1": 0,
  "c1_mp2": 0,
  "c2_mp1": 0,
  "c2_mp2": 0,
  "c3_mp1": 0,
  "c3_mp2": 0
},{
  "_id": {
    "$oid": "6062b0627f26a94399cab5db"
  },
  "username": "iit2019141",
  "c1_sub1": 15,
  "c1_sub2": 15,
  "c1_sub3": 15,
  "c1_sub4": 15,
  "c1_sub5": 15,
  "c2_sub1": 15,
  "c2_sub2": 15,
  "c2_sub3": 15,
  "c2_sub4": 15,
  "c2_sub5": 15,
  "c3_sub1": 25,
  "c3_sub2": 25,
  "c3_sub3": 25,
  "c3_sub4": 25,
  "c3_sub5": 25,
  "sub1": "Design and Analysis of Algorithms",
  "sub2": "Principles of Programming Language",
  "sub3": "Computer Networks",
  "sub4": "Software Engineering",
  "sub5": "Database Management System",
  "c1_ele1": 0,
  "c1_ele2": 0,
  "c1_ele3": 0,
  "c2_ele1": 0,
  "c2_ele2": 0,
  "c2_ele3": 0,
  "c3_ele1": 0,
  "c3_ele2": 0,
  "c3_ele3": 0,
  "ele1": "-",
  "ele2": "-",
  "ele3": "-",
  "mp1": "-",
  "mp2": "-",
  "c1_mp1": 0,
  "c1_mp2": 0,
  "c2_mp1": 0,
  "c2_mp2": 0,
  "c3_mp1": 0,
  "c3_mp2": 0
},{
  "_id": {
    "$oid": "6062b0727f26a94399cab5dc"
  },
  "username": "iit2019149",
  "c1_sub1": 15,
  "c1_sub2": 15,
  "c1_sub3": 15,
  "c1_sub4": 15,
  "c1_sub5": 15,
  "c2_sub1": 15,
  "c2_sub2": 15,
  "c2_sub3": 15,
  "c2_sub4": 15,
  "c2_sub5": 15,
  "c3_sub1": 25,
  "c3_sub2": 25,
  "c3_sub3": 25,
  "c3_sub4": 25,
  "c3_sub5": 25,
  "sub1": "Design and Analysis of Algorithms",
  "sub2": "Principles of Programming Language",
  "sub3": "Computer Networks",
  "sub4": "Software Engineering",
  "sub5": "Database Management System",
  "c1_ele1": 0,
  "c1_ele2": 0,
  "c1_ele3": 0,
  "c2_ele1": 0,
  "c2_ele2": 0,
  "c2_ele3": 0,
  "c3_ele1": 0,
  "c3_ele2": 0,
  "c3_ele3": 0,
  "ele1": "-",
  "ele2": "-",
  "ele3": "-",
  "mp1": "-",
  "mp2": "-",
  "c1_mp1": 0,
  "c1_mp2": 0,
  "c2_mp1": 0,
  "c2_mp2": 0,
  "c3_mp1": 0,
  "c3_mp2": 0
},{
  "_id": {
    "$oid": "60658677bac7a268121db032"
  },
  "username": "iit2018082",
  "c1_sub1": 15,
  "c1_sub2": 0,
  "c1_sub3": 0,
  "c1_sub4": 0,
  "c1_sub5": 0,
  "c2_sub1": 15,
  "c2_sub2": 0,
  "c2_sub3": 0,
  "c2_sub4": 0,
  "c2_sub5": 0,
  "c3_sub1": 25,
  "c3_sub2": 0,
  "c3_sub3": 0,
  "c3_sub4": 0,
  "c3_sub5": 0,
  "sub1": "Data Mining",
  "sub2": "-",
  "sub3": "-",
  "sub4": "-",
  "sub5": "-",
  "c1_ele1": 15,
  "c1_ele2": 15,
  "c1_ele3": 15,
  "c2_ele1": 15,
  "c2_ele2": 15,
  "c2_ele3": 15,
  "c3_ele1": 25,
  "c3_ele2": 25,
  "c3_ele3": 25,
  "ele1": "Convex Optimization",
  "ele2": "Pattern Recognition",
  "ele3": "Advanced data analytics",
  "mp1": "Biometrics",
  "mp2": "-",
  "c1_mp1": 30,
  "c1_mp2": 0,
  "c2_mp1": 30,
  "c2_mp2": 0,
  "c3_mp1": 40,
  "c3_mp2": 0
}]